README.md
setup.cfg
setup.py
sequman/__init__.py
sequman/sequman.py
sequman.egg-info/PKG-INFO
sequman.egg-info/SOURCES.txt
sequman.egg-info/dependency_links.txt
sequman.egg-info/requires.txt
sequman.egg-info/top_level.txt