Metadata-Version: 1.1
Name: sequman
Version: 0.0.2
Summary: functions for routine work with sequence data
Home-page: https://github.com/babinyurii/sequman
Author: Yuriy Babin
Author-email: babin.yurii@gmail.com
License: MIT
Download-URL: https://github.com/babinyurii/sequman/archive/v_0.0.2.tar.gz
Keywords: bioinformatics,sequencing
Platform: UNKNOWN
Classifier: Development Status :: 4 - Beta
Classifier: Intended Audience :: Developers
Classifier: Topic :: Software Development :: Build Tools
Classifier: License :: OSI Approved :: MIT License
Classifier: Programming Language :: Python :: 3
Classifier: Programming Language :: Python :: 3.4
Classifier: Programming Language :: Python :: 3.5
Classifier: Programming Language :: Python :: 3.6
